pluraldo/__init__.py
pluraldo/__main__.py
pluraldo/mimestore.py
pluraldo/pstore.py
pluraldo/tui/task.py
pluraldo/tui/task.tcss
pluraldo-0.1.0.dist-info/METADATA
pluraldo-0.1.0.dist-info/WHEEL
pluraldo-0.1.0.dist-info/entry_points.txt
pluraldo-0.1.0.dist-info/RECORD
